nys_client/__init__.py
nys_client/base.py
nys_client/bot.py
nys_client/client.py
nys_client/events.py
nys_client/inventory_view.py
nys_client/job.py
nys_client/loads.py
nys_client/request.py
nys_client/requests_and_jobs_view.py
nys_client/skus.py
nys_client/system.py
nys_client/utils.py
nys_client-0.2.1.dist-info/licenses/LICENSE
nys_client-0.2.1.dist-info/METADATA
nys_client-0.2.1.dist-info/WHEEL
nys_client-0.2.1.dist-info/top_level.txt
nys_client-0.2.1.dist-info/RECORD
