Metadata-Version: 2.4
Name: nys_client
Version: 0.2.1
Summary: Python client library for the Noyes API
Author: Noyes
Author-email: support@noyes-tech.com
Classifier: Development Status :: 3 - Alpha
Classifier: Intended Audience :: Developers
Classifier: License :: OSI Approved :: MIT License
Classifier: Programming Language :: Python :: 3
Classifier: Programming Language :: Python :: 3.8
Classifier: Programming Language :: Python :: 3.9
Classifier: Programming Language :: Python :: 3.10
Classifier: Programming Language :: Python :: 3.11
Requires-Python: >=3.8
License-File: LICENSE
Requires-Dist: requests>=2.28.1
Requires-Dist: python-dotenv>=1.0.0
Requires-Dist: typing-extensions>=4.12.2
Requires-Dist: pydantic<2.0.0,>=1.10.0
Requires-Dist: fastapi-pagination>=0.12.0
Requires-Dist: nys_schemas<0.4.0,>=0.3.0
Dynamic: author
Dynamic: author-email
Dynamic: classifier
Dynamic: description
Dynamic: description-content-type
Dynamic: license-file
Dynamic: requires-dist
Dynamic: requires-python
Dynamic: summary
